{
    "id": "cb-tvm-identity",
    "name": "Identity Token Vending Machine",
    "source": "github",
    "description" : "The Amazon Web Services Identity Token Vending Machine (TVM) sample application for the CloudBees PaaS",
    "doc-url" : "https://github.com/mqprichard/cb-tvm-identity/blob/master/README.md",
    "icon" : "https://d3ko533tu1ozfq.cloudfront.net/clickstart/sencha_icon.png",

    "build-with-jenkins": {
        "plugins" : ["git"],
        "template": {
            "type": "https://raw.github.com/mqprichard/cb-tvm-identity/master/jenkins-config.xml",
            "options": {
            }
        }
    }
}

